LICENSE
MANIFEST.in
NOTICE
setup.py
TrebuchetTrigger.egg-info/PKG-INFO
TrebuchetTrigger.egg-info/SOURCES.txt
TrebuchetTrigger.egg-info/dependency_links.txt
TrebuchetTrigger.egg-info/entry_points.txt
TrebuchetTrigger.egg-info/requires.txt
TrebuchetTrigger.egg-info/top_level.txt
trigger/__init__.py
trigger/config.py
trigger/extension.py
trigger/shell.py
trigger/drivers/__init__.py
trigger/drivers/trebuchet/__init__.py
trigger/drivers/trebuchet/local.py
trigger/utils/__init__.py
trigger/utils/submodule_update.py