Metadata-Version: 1.0
Name: TrebuchetTrigger
Version: 0.5.1
Summary: An extendable git interface to trebuchet.
Home-page: https://github.com/trebuchet-deploy/trigger
Author: Ryan Lane
Author-email: ryan@ryandlane.com
License: apache2
Platform: UNKNOWN
